<annotation>
	<folder>images</folder>
	<filename>no_mask (32).jpg</filename>
	<path>C:\Users\yifan\Documents\Tensorflow Models\workspace\training_demo\images\no_mask (32).jpg</path>
	<source>
		<database>Unknown</database>
	</source>
	<size>
		<width>700</width>
		<height>443</height>
		<depth>3</depth>
	</size>
	<segmented>0</segmented>
	<object>
		<name>bare</name>
		<pose>Unspecified</pose>
		<truncated>0</truncated>
		<difficult>0</difficult>
		<bndbox>
			<xmin>247</xmin>
			<ymin>231</ymin>
			<xmax>434</xmax>
			<ymax>366</ymax>
		</bndbox>
	</object>
</annotation>
