<annotation>
	<folder>images</folder>
	<filename>surgical_masks (33).jpg</filename>
	<path>C:\Users\yifan\Documents\Tensorflow Models\workspace\training_demo\images\surgical_masks (33).jpg</path>
	<source>
		<database>Unknown</database>
	</source>
	<size>
		<width>750</width>
		<height>445</height>
		<depth>3</depth>
	</size>
	<segmented>0</segmented>
	<object>
		<name>surgical</name>
		<pose>Unspecified</pose>
		<truncated>0</truncated>
		<difficult>0</difficult>
		<bndbox>
			<xmin>185</xmin>
			<ymin>229</ymin>
			<xmax>292</xmax>
			<ymax>309</ymax>
		</bndbox>
	</object>
	<object>
		<name>surgical</name>
		<pose>Unspecified</pose>
		<truncated>0</truncated>
		<difficult>0</difficult>
		<bndbox>
			<xmin>326</xmin>
			<ymin>111</ymin>
			<xmax>424</xmax>
			<ymax>216</ymax>
		</bndbox>
	</object>
</annotation>
