<annotation>
	<folder>images</folder>
	<filename>no_mask (159).jpg</filename>
	<path>C:\Users\yifan\Documents\Tensorflow Models\workspace\training_demo\images\no_mask (159).jpg</path>
	<source>
		<database>Unknown</database>
	</source>
	<size>
		<width>3410</width>
		<height>1906</height>
		<depth>3</depth>
	</size>
	<segmented>0</segmented>
	<object>
		<name>bare</name>
		<pose>Unspecified</pose>
		<truncated>0</truncated>
		<difficult>0</difficult>
		<bndbox>
			<xmin>1364</xmin>
			<ymin>941</ymin>
			<xmax>2182</xmax>
			<ymax>1460</ymax>
		</bndbox>
	</object>
</annotation>
