<annotation>
	<folder>images</folder>
	<filename>no_mask (146).jpg</filename>
	<path>C:\Users\yifan\Documents\Tensorflow Models\workspace\training_demo\images\no_mask (146).jpg</path>
	<source>
		<database>Unknown</database>
	</source>
	<size>
		<width>948</width>
		<height>557</height>
		<depth>3</depth>
	</size>
	<segmented>0</segmented>
	<object>
		<name>bare</name>
		<pose>Unspecified</pose>
		<truncated>0</truncated>
		<difficult>0</difficult>
		<bndbox>
			<xmin>333</xmin>
			<ymin>175</ymin>
			<xmax>480</xmax>
			<ymax>321</ymax>
		</bndbox>
	</object>
</annotation>
